import_export_extensions/__init__.py
import_export_extensions/apps.py
import_export_extensions/fields.py
import_export_extensions/forms.py
import_export_extensions/resources.py
import_export_extensions/tasks.py
import_export_extensions/utils.py
import_export_extensions/widgets.py
import_export_extensions/admin/__init__.py
import_export_extensions/admin/widgets.py
import_export_extensions/admin/forms/__init__.py
import_export_extensions/admin/forms/export_admin_form.py
import_export_extensions/admin/forms/import_admin_form.py
import_export_extensions/admin/mixins/__init__.py
import_export_extensions/admin/mixins/base.py
import_export_extensions/admin/mixins/export_mixin.py
import_export_extensions/admin/mixins/import_export_mixin.py
import_export_extensions/admin/mixins/import_mixin.py
import_export_extensions/admin/model_admins/__init__.py
import_export_extensions/admin/model_admins/export_job_admin.py
import_export_extensions/admin/model_admins/import_job_admin.py
import_export_extensions/admin/model_admins/mixins.py
import_export_extensions/api/__init__.py
import_export_extensions/api/serializers/__init__.py
import_export_extensions/api/serializers/export_job.py
import_export_extensions/api/serializers/import_job.py
import_export_extensions/api/serializers/progress.py
import_export_extensions/api/views/__init__.py
import_export_extensions/api/views/export_job.py
import_export_extensions/api/views/import_job.py
import_export_extensions/migrations/0001_initial.py
import_export_extensions/migrations/__init__.py
import_export_extensions/models/__init__.py
import_export_extensions/models/core.py
import_export_extensions/models/export_job.py
import_export_extensions/models/import_job.py
import_export_extensions/models/tools.py
import_export_extensions/static/import_export_jobs/css/admin/admin.css
import_export_extensions/static/import_export_jobs/css/widgets/progress_bar.css
import_export_extensions/static/import_export_jobs/js/admin/admin.js
import_export_extensions-0.1.0.dist-info/AUTHORS.rst
import_export_extensions-0.1.0.dist-info/LICENSE
import_export_extensions-0.1.0.dist-info/METADATA
import_export_extensions-0.1.0.dist-info/WHEEL
import_export_extensions-0.1.0.dist-info/entry_points.txt
import_export_extensions-0.1.0.dist-info/top_level.txt
import_export_extensions-0.1.0.dist-info/RECORD
