Metadata-Version: 2.1
Name: import-export-extensions
Version: 0.1.0
Summary: TODO: There should be description
Home-page: https://github.com/saritasa-nest/django-import-export-extensions
Author: Saritasa
Author-email: pypi@saritasa.com
License: MIT license
Keywords: import_export_extensions
Classifier: Development Status :: 2 - Pre-Alpha
Classifier: Intended Audience :: Developers
Classifier: License :: OSI Approved :: MIT License
Classifier: Natural Language :: English
Classifier: Framework :: Django
Classifier: Framework :: Django :: 3.2
Classifier: Framework :: Django :: 4.0
Classifier: Framework :: Django :: 4.1
Classifier: Framework :: Django :: 4.2
Classifier: Programming Language :: Python :: 3
Classifier: Programming Language :: Python :: 3.9
Classifier: Programming Language :: Python :: 3.10
Classifier: Programming Language :: Python :: 3.11
Requires-Python: >=3.9
License-File: LICENSE
License-File: AUTHORS.rst
Requires-Dist: django-import-export
Requires-Dist: celery
Requires-Dist: redis
Requires-Dist: django (>=3.2)
Requires-Dist: django-object-actions
Requires-Dist: django-picklefield
Requires-Dist: django-filter
Requires-Dist: requests
Requires-Dist: psycopg2-binary
